Metadata-Version: 1.1
Name: escapejson
Version: 0.2
Summary: Escape JSON strings for safe execution as literal javascript and inclusion in HTML <script> environments
Home-page: https://github.com/yourcelf/escapejson
Author: Charlie DeTar
Author-email: cfd@mdia.mit.edu
License: BSD License
Platform: UNKNOWN
Classifier: Environment :: Web Environment
Classifier: Framework :: Django
Classifier: Framework :: Django :: 1.9
Classifier: Intended Audience :: Developers
Classifier: License :: OSI Approved :: BSD License
Classifier: Operating System :: OS Independent
Classifier: Programming Language :: Python
Classifier: Programming Language :: Python :: 3
Classifier: Programming Language :: Python :: 3.4
Classifier: Programming Language :: Python :: 3.5
Classifier: Topic :: Internet :: WWW/HTTP
Classifier: Topic :: Internet :: WWW/HTTP :: Dynamic Content
